improved_replace/__init__.py
improved_replace/core.py
improved_replace-1.3.2.dist-info/LICENSE
improved_replace-1.3.2.dist-info/METADATA
improved_replace-1.3.2.dist-info/WHEEL
improved_replace-1.3.2.dist-info/top_level.txt
improved_replace-1.3.2.dist-info/RECORD
