Metadata-Version: 2.1
Name: improved-replace
Version: 1.3.2
Summary: Add replace method improvements
Home-page: https://github.com/LuckJMG/ImprovedReplace
Author: LuckJMG
Author-email: lucas.mosquera13@gmail.com
License: MIT license
Platform: OS Independent
Classifier: Programming Language :: Python :: 3
Classifier: License :: OSI Approved :: MIT License
Classifier: Operating System :: OS Independent
Requires-Python: >=3.6
